just_dna_module/__init__.py
just_dna_module-0.0.1.dist-info/LICENSE
just_dna_module-0.0.1.dist-info/METADATA
just_dna_module-0.0.1.dist-info/WHEEL
just_dna_module-0.0.1.dist-info/top_level.txt
just_dna_module-0.0.1.dist-info/RECORD
