Metadata-Version: 2.1
Name: just-dna-module
Version: 0.0.1
Summary: Just DNA Module
Author: Anton Kulaga
Author-email: antonkulaga@gmail.com
Classifier: Programming Language :: Python :: 3
Classifier: License :: OSI Approved :: MIT License
Classifier: Operating System :: OS Independent
Requires-Python: >=3.11
License-File: LICENSE
Requires-Dist: oakvar
